MqttLibPy/__init__.py
MqttLibPy/client.py
MqttLibPy/serializer.py
mqttlibpy-1.5.2.dist-info/METADATA
mqttlibpy-1.5.2.dist-info/WHEEL
mqttlibpy-1.5.2.dist-info/licenses/LICENSE
mqttlibpy-1.5.2.dist-info/RECORD
