Metadata-Version: 2.4
Name: MqttLibPy
Version: 1.5.2
Summary: A small example package
Project-URL: Homepage, https://github.com/xmarts/mqtt-common
Project-URL: Bug Tracker, https://github.com/xmarts/mqtt-common/issues
Author-email: juan pablo allende - xmarts <juan.allende@xmarts.com>
License-File: LICENSE
Classifier: License :: OSI Approved :: MIT License
Classifier: Operating System :: OS Independent
Classifier: Programming Language :: Python :: 3
Requires-Python: >=3.7
Requires-Dist: cryptography
Requires-Dist: paho-mqtt==1.6.1
Requires-Dist: psycopg2
